wmbc/__init__.py
wmbc/__main__.py
wmbc/wmbc.py
wmbc-1.0.5.dist-info/METADATA
wmbc-1.0.5.dist-info/WHEEL
wmbc-1.0.5.dist-info/licenses/LICENSE
wmbc-1.0.5.dist-info/RECORD
