Metadata-Version: 2.4
Name: wmbc
Version: 1.0.5
Summary: Wireless Modbus Bridge Controller
License: Apache-2.0
License-File: LICENSE
Author: Jan Kowalewski
Author-email: <jkowalewski@cthings.co>
Maintainer: Jan Kowalewski
Maintainer-email: <jkowalewski@cthings.co>
Requires-Python: >=3.11,<4.0
Classifier: License :: OSI Approved :: Apache Software License
Classifier: Programming Language :: Python :: 3
Classifier: Programming Language :: Python :: 3.11
Classifier: Programming Language :: Python :: 3.12
Classifier: Programming Language :: Python :: 3.13
Classifier: Programming Language :: Python :: 3.14
Requires-Dist: crccheck (>=1.3.0)
Requires-Dist: mbproto (>=1.0.2)
Requires-Dist: wirepas-gateway (>=1.5.0)
Requires-Dist: wsctrl (>=1.0.2)
